geonadir_upload_cli/__init__.py
geonadir_upload_cli/__main__.py
geonadir_upload_cli/__version__.py
geonadir_upload_cli/cli.py
geonadir_upload_cli/dataset.py
geonadir_upload_cli/parallel.py
geonadir_upload_cli/upload.py
geonadir_upload_cli/util.py
geonadir_upload_cli-2.2.1.3.dist-info/LICENSE
geonadir_upload_cli-2.2.1.3.dist-info/METADATA
geonadir_upload_cli-2.2.1.3.dist-info/WHEEL
geonadir_upload_cli-2.2.1.3.dist-info/entry_points.txt
geonadir_upload_cli-2.2.1.3.dist-info/top_level.txt
geonadir_upload_cli-2.2.1.3.dist-info/RECORD
