Metadata-Version: 2.1
Name: geonadir-upload-cli
Version: 2.2.1.3
Summary: Geonadir upload CLI tool.
Author-email: T Lan <t.lan@uq.edu.au>, Joan Li <joan@geonadir.com>
License: MIT
Project-URL: homepage, https://github.com/geonadir/geonadir-upload-cli
Classifier: License :: OSI Approved :: MIT License
Classifier: Programming Language :: Python
Classifier: Programming Language :: Python :: 3
Requires-Python: >=3.8.0
License-File: LICENSE
Requires-Dist: click
Requires-Dist: pandas
Requires-Dist: pystac
Requires-Dist: requests
Requires-Dist: tqdm
